florent_bossart_de_toolkit/__init__.py
florent_bossart_de_toolkit-0.1.0.dist-info/METADATA
florent_bossart_de_toolkit-0.1.0.dist-info/WHEEL
florent_bossart_de_toolkit-0.1.0.dist-info/entry_points.txt
florent_bossart_de_toolkit-0.1.0.dist-info/RECORD
