Metadata-Version: 2.3
Name: florent-bossart-de-toolkit
Version: 0.1.0
Summary: 
Author: Florent Bossart
Author-email: florent.bossart@gmail.com
Requires-Python: >=3.12
Classifier: Programming Language :: Python :: 3
Classifier: Programming Language :: Python :: 3.12
Classifier: Programming Language :: Python :: 3.13
Requires-Dist: click (>=8.1.8,<9.0.0)
